protectonce_native-0.1.28b2.data/purelib/protectonce_native/__init__.py
protectonce_native-0.1.28b2.data/purelib/protectonce_native/core/core.js
protectonce_native-0.1.28b2.data/purelib/protectonce_native/out/libagent_core.so
protectonce_native-0.1.28b2.data/purelib/protectonce_native/runtimes/__init__.py
protectonce_native-0.1.28b2.data/purelib/protectonce_native/runtimes/python/__init__.py
protectonce_native-0.1.28b2.data/purelib/protectonce_native/runtimes/python/protect_once_py_interface.py
protectonce_native-0.1.28b2.dist-info/METADATA
protectonce_native-0.1.28b2.dist-info/WHEEL
protectonce_native-0.1.28b2.dist-info/top_level.txt
protectonce_native-0.1.28b2.dist-info/RECORD
