Metadata-Version: 2.1
Name: protectonce-native
Version: 0.1.28b2
Summary: python agent interface native package
Home-page: https://github.com/ProtectOnce/agent_interface.git
Author: protectonce
Author-email: protectonce@protectonce.com
License: UNKNOWN
Platform: UNKNOWN
Classifier: Programming Language :: Python :: 3
Classifier: Operating System :: OS Independent
